cotyledon/__init__.py
cotyledon/_service.py
cotyledon/_service_manager.py
cotyledon/_utils.py
cotyledon/oslo_config_glue.py
cotyledon/tests/__init__.py
cotyledon/tests/base.py
cotyledon/tests/examples.py
cotyledon/tests/test_functional.py
cotyledon/tests/test_unit.py
cotyledon-2.0.0.dist-info/LICENSE
cotyledon-2.0.0.dist-info/METADATA
cotyledon-2.0.0.dist-info/WHEEL
cotyledon-2.0.0.dist-info/entry_points.txt
cotyledon-2.0.0.dist-info/top_level.txt
cotyledon-2.0.0.dist-info/RECORD
