Metadata-Version: 2.2
Name: cotyledon
Version: 2.0.0
Summary: Cotyledon provides a framework for defining long-running services.
Author-email: Mehdi Abaakouk <sileht@sileht.net>
Project-URL: Home Page, https://github.com/sileht/cotyledon
Classifier: Intended Audience :: Information Technology
Classifier: Intended Audience :: System Administrators
Classifier: License :: OSI Approved :: Apache Software License
Classifier: Operating System :: POSIX :: Linux
Classifier: Programming Language :: Python
Classifier: Programming Language :: Python :: 3
Classifier: Programming Language :: Python :: 3.9
Classifier: Programming Language :: Python :: 3.10
Classifier: Programming Language :: Python :: 3.11
Classifier: Programming Language :: Python :: 3.12
Requires-Python: >=3.9
License-File: LICENSE
Requires-Dist: setproctitle; sys_platform != "win32"
Provides-Extra: test
Requires-Dist: mock; extra == "test"
Requires-Dist: pytest; extra == "test"
Requires-Dist: pytest-cov; extra == "test"
Requires-Dist: pytest-xdist; extra == "test"
Provides-Extra: oslo
Requires-Dist: oslo.config>=3.14.0; extra == "oslo"
Provides-Extra: doc
Requires-Dist: sphinx_rtd_theme; extra == "doc"
Requires-Dist: sphinx; extra == "doc"
